plug_in/plugin2/constants.py
plug_in_plugin2-1.0.4.dist-info/METADATA
plug_in_plugin2-1.0.4.dist-info/WHEEL
plug_in_plugin2-1.0.4.dist-info/top_level.txt
plug_in_plugin2-1.0.4.dist-info/RECORD
