Metadata-Version: 2.1
Name: plug-in-plugin2
Version: 1.0.4
Summary: Plugin 2
License: Plug-in Software License Agreement
